fastapi_startkit/__init__.py
fastapi_startkit/application.py
fastapi_startkit/configuration/Configuration.py
fastapi_startkit/configuration/__init__.py
fastapi_startkit/configuration/helpers.py
fastapi_startkit/configuration/providers/ConfigurationProvider.py
fastapi_startkit/configuration/providers/__init__.py
fastapi_startkit/container/__init__.py
fastapi_startkit/container/container.py
fastapi_startkit/environment/environment.py
fastapi_startkit/exceptions/DD.py
fastapi_startkit/exceptions/ExceptionHandler.py
fastapi_startkit/exceptions/__init__.py
fastapi_startkit/exceptions/exceptionite/__init__.py
fastapi_startkit/exceptions/exceptionite/blocks.py
fastapi_startkit/exceptions/exceptionite/controllers.py
fastapi_startkit/exceptions/exceptionite/solutions.py
fastapi_startkit/exceptions/exceptionite/tabs.py
fastapi_startkit/exceptions/exceptions.py
fastapi_startkit/exceptions/handlers/DumpExceptionHandler.py
fastapi_startkit/exceptions/handlers/HttpExceptionHandler.py
fastapi_startkit/exceptions/handlers/ModelNotFoundHandler.py
fastapi_startkit/facades/Auth.py
fastapi_startkit/facades/Auth.pyi
fastapi_startkit/facades/Broadcast.py
fastapi_startkit/facades/Cache.py
fastapi_startkit/facades/Config.py
fastapi_startkit/facades/Config.pyi
fastapi_startkit/facades/Dump.py
fastapi_startkit/facades/Dump.pyi
fastapi_startkit/facades/Facade.py
fastapi_startkit/facades/Gate.py
fastapi_startkit/facades/Gate.pyi
fastapi_startkit/facades/Hash.py
fastapi_startkit/facades/Hash.pyi
fastapi_startkit/facades/Loader.py
fastapi_startkit/facades/Loader.pyi
fastapi_startkit/facades/Mail.py
fastapi_startkit/facades/Mail.pyi
fastapi_startkit/facades/Notification.py
fastapi_startkit/facades/Notification.pyi
fastapi_startkit/facades/Queue.py
fastapi_startkit/facades/Queue.pyi
fastapi_startkit/facades/RateLimiter.py
fastapi_startkit/facades/RateLimiter.pyi
fastapi_startkit/facades/Request.py
fastapi_startkit/facades/Request.pyi
fastapi_startkit/facades/Response.py
fastapi_startkit-0.1.3.dist-info/METADATA
fastapi_startkit-0.1.3.dist-info/WHEEL
fastapi_startkit-0.1.3.dist-info/RECORD
