Metadata-Version: 2.4
Name: fastapi-startkit
Version: 0.1.3
Summary: Fastapi_Startkit components
Author: Bedram Tamang
Author-email: tmgbedu@gmail.com
Requires-Python: >=3.12,<4.0
Classifier: Programming Language :: Python :: 3
Classifier: Programming Language :: Python :: 3.12
Classifier: Programming Language :: Python :: 3.13
Classifier: Programming Language :: Python :: 3.14
Requires-Dist: dotty-dict (>=1.3.1)
Requires-Dist: fastapi[standard] (>=0.124.4,<0.125.0)
